qyc_env/__init__.py
qyc_env-0.0.1.dist-info/METADATA
qyc_env-0.0.1.dist-info/WHEEL
qyc_env-0.0.1.dist-info/top_level.txt
qyc_env-0.0.1.dist-info/RECORD
