Metadata-Version: 2.1
Name: qyc-env
Version: 0.0.1
Summary: A OpenAI Gym for qyc
Home-page: UNKNOWN
License: UNKNOWN
Platform: UNKNOWN
Requires-Dist: gym
